<annotation>
	<folder>img</folder>
	<filename>puck330.jpg</filename>
	<path>/Users/mpittinsky/chexx/data/img/puck330.jpg</path>
	<source>
		<database>Unknown</database>
	</source>
	<size>
		<width>1920</width>
		<height>1080</height>
		<depth>3</depth>
	</size>
	<segmented>0</segmented>
	<object>
		<name>puck</name>
		<pose>Unspecified</pose>
		<truncated>0</truncated>
		<difficult>0</difficult>
		<bndbox>
			<xmin>345</xmin>
			<ymin>713</ymin>
			<xmax>387</xmax>
			<ymax>742</ymax>
		</bndbox>
	</object>
</annotation>
